mmm/BaseModel.py
mmm/DataSplit.py
mmm/__init__.py
mmm/app.py
mmm/augmentations.py
mmm/bucketizing.py
mmm/data_loading/ClassificationDataset.py
mmm/data_loading/DetectionDataset.py
mmm/data_loading/DiskDataset.py
mmm/data_loading/DistributedPath.py
mmm/data_loading/ImageCaptionDataset.py
mmm/data_loading/ImageGenerationDataset.py
mmm/data_loading/MTLDataset.py
mmm/data_loading/MultiLabelSemSegDataset.py
mmm/data_loading/MultilabelClassificationDataset.py
mmm/data_loading/MultipleInstanceDataset.py
mmm/data_loading/RegressionDataset.py
mmm/data_loading/SemSegDataset.py
mmm/data_loading/TrainValCohort.py
mmm/data_loading/__init__.py
mmm/data_loading/geojson/AnnoFilterConfig.py
mmm/data_loading/geojson/GeoAnno.py
mmm/data_loading/geojson/GeojsonObjWindows.py
mmm/data_loading/geojson/GeojsonRegionWindows.py
mmm/data_loading/geojson/NoUsefulWindowException.py
mmm/data_loading/geojson/WSIGeojsonDataset.py
mmm/data_loading/geojson/__init__.py
mmm/data_loading/geojson/utils.py
mmm/data_loading/medical/__init__.py
mmm/data_loading/medical/wsi_service.py
mmm/data_loading/non_medical/__init__.py
mmm/data_loading/s3.py
mmm/data_loading/ssl.py
mmm/data_loading/synthetic/__init__.py
mmm/data_loading/synthetic/artifact.py
mmm/data_loading/synthetic/mockup.py
mmm/data_loading/synthetic/shape_dataset.py
mmm/data_loading/utils.py
mmm/event_selectors.py
mmm/inference_app.py
mmm/interactive/__init__.py
mmm/interactive/blocks.py
mmm/interactive/configs.py
mmm/interactive/data.py
mmm/interactive/pipes.py
mmm/interactive/tasks.py
mmm/interactive/training.py
mmm/interactive/utils.py
mmm/labelstudio_ext/DLModel.py
mmm/labelstudio_ext/LGBModel.py
mmm/labelstudio_ext/LSDataset.py
mmm/labelstudio_ext/LSModel.py
mmm/labelstudio_ext/LabelstudioCredentials.py
mmm/labelstudio_ext/NativeBlocks.py
mmm/labelstudio_ext/__init__.py
mmm/labelstudio_ext/projects.py
mmm/labelstudio_ext/utils.py
mmm/logging/__init__.py
mmm/logging/st_ext.py
mmm/logging/type_ext.py
mmm/logging/wandb_ext.py
medicalmultitaskmodeling-1.0.4.dist-info/METADATA
medicalmultitaskmodeling-1.0.4.dist-info/WHEEL
medicalmultitaskmodeling-1.0.4.dist-info/entry_points.txt
medicalmultitaskmodeling-1.0.4.dist-info/RECORD
