Metadata-Version: 2.1
Name: MedicalMultitaskModeling
Version: 1.0.4
Summary: Multitask learning framework for medical data
License: All rights reserved.
Author: Raphael Schäfer
Author-email: jan.raphael.schaefer@mevis.fraunhofer.de
Requires-Python: >=3.10,<3.12
Classifier: License :: Other/Proprietary License
Classifier: Programming Language :: Python :: 3
Classifier: Programming Language :: Python :: 3.10
Classifier: Programming Language :: Python :: 3.11
Provides-Extra: all
Provides-Extra: api
Provides-Extra: detection
Provides-Extra: export
Provides-Extra: interactive
Provides-Extra: testing
Requires-Dist: aiohttp (>=3.9.0,<4.0.0) ; extra == "all" or extra == "api"
Requires-Dist: albumentations (>=1.4.11,<2.0.0)
Requires-Dist: autodoc-pydantic (>=2.2.0,<3.0.0) ; extra == "all" or extra == "testing"
Requires-Dist: black (>=23.1.0,<24.0.0) ; extra == "all" or extra == "all" or extra == "all" or extra == "interactive" or extra == "testing"
Requires-Dist: deepdiff (>=6.6.1,<7.0.0)
Requires-Dist: fastapi[all] (>=0.110.2,<0.111.0) ; extra == "all" or extra == "api"
Requires-Dist: fsspec[s3] (>=2024.3.1,<2025.0.0)
Requires-Dist: imageio (>=2.31.5,<3.0.0)
Requires-Dist: ipykernel (>=6.25.2,<7.0.0) ; extra == "all" or extra == "all" or extra == "interactive"
Requires-Dist: ipywidgets (>=8.1.1,<9.0.0) ; extra == "all" or extra == "all" or extra == "interactive"
Requires-Dist: isort (>=5.10.1,<6.0.0) ; extra == "all" or extra == "testing"
Requires-Dist: json5 (>=0.9.14,<0.10.0)
Requires-Dist: label-studio-converter (>=0.0.58,<0.0.59) ; extra == "all" or extra == "api"
Requires-Dist: label-studio-sdk (>=0.0.34,<0.0.35) ; extra == "all" or extra == "api"
Requires-Dist: lightgbm (>=4.1.0,<5.0.0) ; extra == "all" or extra == "api"
Requires-Dist: matplotlib (>=3.8.0,<4.0.0) ; extra == "all" or extra == "all" or extra == "interactive"
Requires-Dist: minio (>=7.1.17,<8.0.0)
Requires-Dist: mmdet (>=3.2.0,<4.0.0) ; extra == "all" or extra == "detection"
Requires-Dist: monai (>=1.3.0,<2.0.0)
Requires-Dist: nbconvert (>=7.16.1,<8.0.0) ; extra == "all" or extra == "all" or extra == "interactive"
Requires-Dist: nbformat (>=5.9.2,<6.0.0) ; extra == "all" or extra == "all" or extra == "interactive"
Requires-Dist: nibabel (>=5.2.1,<6.0.0)
Requires-Dist: numpy (>=1.26.1,<2.0.0)
Requires-Dist: onnx (>=1.13.1,<2.0.0) ; extra == "all" or extra == "export"
Requires-Dist: onnxruntime (>=1.14.1,<2.0.0) ; extra == "all" or extra == "export"
Requires-Dist: opencv-python (>=4.8.1.78,<5.0.0.0)
Requires-Dist: pandas (>=2.1.1,<3.0.0)
Requires-Dist: patchify (>=0.2.3,<0.3.0)
Requires-Dist: plotly (>=5.17.0,<6.0.0) ; extra == "all" or extra == "all" or extra == "interactive"
Requires-Dist: pydantic (>=2.4.2,<3.0.0)
Requires-Dist: pydantic-settings (>=2.0.3,<3.0.0)
Requires-Dist: pytest (>=8.0.0,<9.0.0) ; extra == "all" or extra == "testing"
Requires-Dist: pytest-cov (>=4.0.0,<5.0.0) ; extra == "all" or extra == "testing"
Requires-Dist: rasterio (>=1.3.9,<2.0.0)
Requires-Dist: scikit-learn (>=1.3.1,<2.0.0)
Requires-Dist: seaborn (>=0.13.0,<0.14.0) ; extra == "all" or extra == "all" or extra == "interactive"
Requires-Dist: segmentation-models-pytorch (>=0.3.3,<0.4.0)
Requires-Dist: shapely (>=2.0.2,<3.0.0)
Requires-Dist: sphinx (>=7.3.7,<8.0.0) ; extra == "all" or extra == "testing"
Requires-Dist: streamlit (>=1.33.0,<2.0.0) ; extra == "all" or extra == "all" or extra == "interactive"
Requires-Dist: tiffslide (>=2.2.0,<3.0.0)
Requires-Dist: toml (>=0.10.2,<0.11.0)
Requires-Dist: torch (>=2.1.2,<3.0.0)
Requires-Dist: torchinfo (>=1.8.0,<2.0.0)
Requires-Dist: torchvision (>=0.16.2,<0.17.0)
Requires-Dist: tqdm (>=4.66.1,<5.0.0)
Requires-Dist: typer (>=0.12.3,<0.13.0)
Requires-Dist: universal-pathlib (>=0.2.2,<0.3.0)
Requires-Dist: wandb (>=0.16.3,<0.17.0)
Requires-Dist: wsi-service (>=0.12.14,<0.13.0) ; extra == "all" or extra == "api"
